windsor/__init__.py
windsor/cdkdependencies.py
windsor/cli.py
windsor/config.py
windsor/main.py
windsor/utils.py
windsor/cookiecutter/apigw-restapi/cookiecutter.json
windsor/cookiecutter/apigw-restapi/{{cookiecutter.cdk_lib}}/constructs/restapi/config.ts
windsor/cookiecutter/apigw-restapi/{{cookiecutter.cdk_lib}}/constructs/restapi/index.ts
windsor/cookiecutter/apigw-restapi/{{cookiecutter.cdk_lib}}/constructs/restapi/routes.ts
windsor/cookiecutter/lambda/cookiecutter.json
windsor/cookiecutter/lambda/{{cookiecutter.cdk_lib}}/constructs/{{cookiecutter.function_name.lower()}}.ts
windsor/cookiecutter/lambda/{{cookiecutter.cdk_lib}}/constructs/lambdas/{{cookiecutter.function_name.lower()}}.ts
windsor/cookiecutter/lambda/{{cookiecutter.cdk_lib}}/handlers/{{cookiecutter.function_name}}/handler.{{cookiecutter.file_extension}}
windsor/cookiecutter/lambda/{{cookiecutter.cdk_lib}}/handlers/{{cookiecutter.function_name}}/test_handler.{{cookiecutter.file_extension}}
windsor/cookiecutter/lambda/{{cookiecutter.cdk_lib}}/handlers/{{cookiecutter.function_name}}/{{cookiecutter.dependencies_file}}
windsor/cookiecutter/react-codepipeline/builspec-example.yaml
windsor/cookiecutter/react-codepipeline/cookiecutter.json
windsor/cookiecutter/react-codepipeline/{{cookiecutter.cdk_lib}}/constructs/react-pipeline.ts
windsor/data/configdefault.json
windsor/data/resources.json
windsor/services/__init__.py
windsor/services/apigw/__init__.py
windsor/services/apigw/restapi.py
windsor/services/codepipeline/__init__.py
windsor/services/codepipeline/react.py
windsor/services/lambda_/__init__.py
windsor/services/lambda_/function.py
windsor/services/lambda_/runtime.py
windsor-1.0.1.dist-info/METADATA
windsor-1.0.1.dist-info/WHEEL
windsor-1.0.1.dist-info/entry_points.txt
windsor-1.0.1.dist-info/top_level.txt
windsor-1.0.1.dist-info/RECORD
