Metadata-Version: 2.1
Name: windsor
Version: 1.0.1
Summary: Bootstrap your AWS CDK project resources by running CLI commands
Home-page: https://github.com/westpoint-io/windsor
Author: Westpoint
License: UNKNOWN
Platform: UNKNOWN
Requires-Python: >=3.6
Requires-Dist: cookiecutter (~=1.7.2)
Requires-Dist: fire
Requires-Dist: marshmallow
